adcutils/__init__.py
adcutils/__version__.py
adcutils/frequency.py
adcutils-0.1.0.dist-info/METADATA
adcutils-0.1.0.dist-info/WHEEL
adcutils-0.1.0.dist-info/licenses/LICENSE
adcutils-0.1.0.dist-info/RECORD
