Metadata-Version: 2.4
Name: adcutils
Version: 0.1.0
Summary: Utility package for ADC measurements and signal analysis
Project-URL: Homepage, https://github.com/jamackey/adcutils
Project-URL: Repository, https://github.com/jamackey/adcutils
Author-email: James Mackey <jamackey.pc@gmail.com>
License: MIT
License-File: LICENSE
Keywords: adc,frequency,measurements,sampling,signal processing
Classifier: License :: OSI Approved :: MIT License
Classifier: Operating System :: OS Independent
Classifier: Programming Language :: Python :: 3
Requires-Python: >=3.8
Requires-Dist: numpy>=1.21
